tts_webui_extension/openai_tts_api/__init__.py
tts_webui_extension/openai_tts_api/extension_metadata.py
tts_webui_extension/openai_tts_api/main.py
tts_webui_extension/openai_tts_api/migrate_config.py
tts_webui_extension/openai_tts_api/router.py
tts_webui_extension/openai_tts_api/threader.py
tts_webui_extension/openai_tts_api/transcribe_audio_file.py
tts_webui_extension/openai_tts_api/api/__init__.py
tts_webui_extension/openai_tts_api/api/audio.py
tts_webui_extension/openai_tts_api/api/info.py
tts_webui_extension/openai_tts_api/api/models.py
tts_webui_extension/openai_tts_api/models/__init__.py
tts_webui_extension/openai_tts_api/models/create_speech_request.py
tts_webui_extension/openai_tts_api/models/response_format.py
tts_webui_extension/openai_tts_api/services/__init__.py
tts_webui_extension/openai_tts_api/services/transcription_service.py
tts_webui_extension/openai_tts_api/services/tts_service.py
tts_webui_extension/openai_tts_api/services/voice_service.py
tts_webui_extension/openai_tts_api/utils/__init__.py
tts_webui_extension/openai_tts_api/utils/audio_utils.py
tts_webui_extension/openai_tts_api/utils/presets.py
tts_webui_extension_openai_tts_api-0.14.0.dist-info/licenses/LICENSE
tts_webui_extension_openai_tts_api-0.14.0.dist-info/METADATA
tts_webui_extension_openai_tts_api-0.14.0.dist-info/WHEEL
tts_webui_extension_openai_tts_api-0.14.0.dist-info/top_level.txt
tts_webui_extension_openai_tts_api-0.14.0.dist-info/RECORD
