Metadata-Version: 2.4
Name: tts_webui_extension.openai_tts_api
Version: 0.14.0
Summary: OpenAI compatible TTS API with support for multiple TTS models
Author: rsxdalv
License: MIT
Project-URL: Homepage, https://github.com/rsxdalv/tts_webui_extension.openai_tts_api
Classifier: Programming Language :: Python :: 3
Classifier: License :: OSI Approved :: MIT License
Classifier: Operating System :: OS Independent
Requires-Python: >=3.7
License-File: LICENSE
Requires-Dist: openai
Requires-Dist: gradio
Requires-Dist: uvicorn
Requires-Dist: psutil
Requires-Dist: fastapi
Requires-Dist: pydantic
Requires-Dist: requests
Requires-Dist: scipy
Requires-Dist: numpy
Provides-Extra: kokoro
Requires-Dist: tts_webui_extension.kokoro; extra == "kokoro"
Provides-Extra: rvc
Requires-Dist: tts_webui_extension.rvc; extra == "rvc"
Provides-Extra: chatterbox
Requires-Dist: tts_webui_extension.chatterbox; extra == "chatterbox"
Provides-Extra: kitten-tts
Requires-Dist: tts_webui_extension.kitten_tts; extra == "kitten-tts"
Provides-Extra: styletts2
Requires-Dist: tts_webui_extension.styletts2; extra == "styletts2"
Provides-Extra: f5-tts
Requires-Dist: tts_webui_extension.f5_tts; extra == "f5-tts"
Dynamic: license-file
